LICENSE
README.md
setup.cfg
setup.py
fbthon/__init__.py
fbthon/__version__.py
fbthon/chats.py
fbthon/comments.py
fbthon/createaccount.py
fbthon/exceptions.py
fbthon/login.py
fbthon/messenger.py
fbthon/posts.py
fbthon/settings.py
fbthon/user.py
fbthon/utils.py
fbthon.egg-info/PKG-INFO
fbthon.egg-info/SOURCES.txt
fbthon.egg-info/dependency_links.txt
fbthon.egg-info/requires.txt
fbthon.egg-info/top_level.txt