Metadata-Version: 2.1
Name: fbthon
Version: 0.0.2
Summary: Simple Facebook scraper
Home-page: https://github.com/MR-X-Junior/fbthon
Author: Rahmat adha
Author-email: rahmadadha11@gmail.com
License: MIT
Keywords: facebook-scraper,facebook-parser,facebook-scraper-without-apikey
Classifier: Development Status :: 3 - Alpha
Classifier: Intended Audience :: Developers
Classifier: Topic :: Software Development :: Build Tools
Classifier: License :: OSI Approved :: MIT License
Classifier: Natural Language :: Indonesian
Classifier: Programming Language :: Python :: 3
Classifier: Programming Language :: Python :: 3.7
Classifier: Programming Language :: Python :: 3.8
Classifier: Programming Language :: Python :: 3.9
Classifier: Programming Language :: Python :: 3.10
Classifier: Programming Language :: Python :: 3.11
Classifier: Programming Language :: Python :: 3 :: Only
Requires-Python: >=3.7
License-File: LICENSE
